fxdc/__init__.py
fxdc/config.py
fxdc/exceptions.py
fxdc/fields.py
fxdc/json.py
fxdc/misc.py
fxdc/read.py
fxdc/write.py
fxdc/defaultclasses/__init__.py
fxdc/defaultclasses/datetimedefaults.py
fxdc/defaultclasses/numpydefaults.py
fxdc/defaultclasses/pandasdefaults.py
fxdc/defaultclasses/pythondefaults.py
fxdc/parsedata/__init__.py
fxdc/parsedata/fxdcobject.py
fxdc/parsedata/lexer.py
fxdc/parsedata/parsedata.py
fxdc/writedata/__init__.py
fxdc/writedata/parseobject.py
tests/test_defaultclasses.py
tests/test_fields.py
tests/test_fxdc_core.py
tests/test_nestedclasses.py
tests/test_userclasses.py
fxdc-5.0.0.dist-info/METADATA
fxdc-5.0.0.dist-info/WHEEL
fxdc-5.0.0.dist-info/top_level.txt
fxdc-5.0.0.dist-info/RECORD
