Metadata-Version: 2.4
Name: fxdc
Version: 5.0.0
Summary: This Package Parses FxDC file and returns the object
Author-email: FedxD <fedxdofficial@gmail.com>
License: MIT
Project-URL: Homepage, https://github.com/KazimFedxD/FedxD-Data-Container
Classifier: Programming Language :: Python :: 3
Classifier: License :: OSI Approved :: MIT License
Classifier: Operating System :: OS Independent
Requires-Python: >=3.10
